calendar_queue-0.2.0.dist-info/METADATA
calendar_queue-0.2.0.dist-info/WHEEL
calendar_queue-0.2.0.dist-info/entry_points.txt
calendar_queue-0.2.0.dist-info/licenses/LICENSE
calendar_queue/__init__.py
calendar_queue/calendar.py
calendar_queue/calendar_queue.py
calendar_queue-0.2.0.dist-info/RECORD
