Metadata-Version: 2.1
Name: calendar-queue
Version: 0.2.0
Summary: A pure python calendar-queue based on asyncio
Author: Claudio Usai
License: MIT
Classifier: Programming Language :: Python :: 3 :: Only
Classifier: Programming Language :: Python :: 3.10
Classifier: Programming Language :: Python :: 3.11
Classifier: Programming Language :: Python :: 3.12
Classifier: Programming Language :: Python :: 3.13
Classifier: Programming Language :: Python :: 3.14
Classifier: License :: OSI Approved :: MIT License
Requires-Python: >=3.10
